demo_rag/__init__.py
demo_rag/api/__init__.py
demo_rag/api/deps.py
demo_rag/api/router.py
demo_rag/card/__init__.py
demo_rag/card/api_schema.py
demo_rag/card/config/__init__.py
demo_rag/card/config/config.py
demo_rag/card/config/rag.py
demo_rag/card/config/storage.py
demo_rag/service/__init__.py
demo_rag/service/document_store_extend.py
demo_rag/service/rag_service.py
demo_rag/service/rag_setting.py
demo_rag-0.0.1.dist-info/METADATA
demo_rag-0.0.1.dist-info/WHEEL
demo_rag-0.0.1.dist-info/top_level.txt
demo_rag-0.0.1.dist-info/RECORD
