Metadata-Version: 2.4
Name: demo-rag
Version: 0.0.1
Summary: A demo project for RAG using FastAPI and LlamaIndex
Author: WH
License: MIT
Project-URL: Homepage, https://github.com/a171232886/demo_rag
Project-URL: Bug Reports, https://github.com/a171232886/demo_rag/issues
Project-URL: Source, https://github.com/a171232886/demo_rag
Project-URL: 视频教程, https://www.bilibili.com/video/BV1u7BvBGEfX
Classifier: Development Status :: 3 - Alpha
Classifier: Intended Audience :: Developers
Classifier: License :: OSI Approved :: MIT License
Classifier: Programming Language :: Python :: 3
Classifier: Programming Language :: Python :: 3.13
Classifier: Operating System :: OS Independent
Classifier: Topic :: Scientific/Engineering :: Artificial Intelligence
Requires-Python: >=3.13
Requires-Dist: fastapi>=0.127.0
Requires-Dist: llama-index>=0.14.10
Requires-Dist: llama-index-embeddings-openai-like>=0.2.2
Requires-Dist: llama-index-llms-openai-like>=0.5.3
Requires-Dist: llama-index-storage-docstore-mongodb>=0.4.1
Requires-Dist: llama-index-storage-index-store-mongodb>=0.5.1
Requires-Dist: llama-index-vector-stores-qdrant>=0.9.0
Requires-Dist: motor>=3.7.1
Requires-Dist: python-pptx>=1.0.2
Requires-Dist: pyyaml>=6.0.3
Requires-Dist: qdrant-client>=1.16.2
Requires-Dist: s3fs>=2025.12.0
Requires-Dist: uvicorn>=0.40.0
